pbr/202106-record-group1.html
pbr/202106-record-group1.xlsx
pbr/202106-record-group2.xlsx
pbr/202106-record-group3.xlsx
pbr/202106-record-group4.xlsx
pbr/202106-record-group5.xlsx
pbr/202106-record-group6.xlsx
pbr/__init__.py
pbr/bridge_score.py
pbr/index-temp.html
pbr/match-temp.html
pbr/pbr.py
pbr/pbr_excel.py
pbr/pbr_gen.py
pbr/pbr_tables.py
pbr/pbr_template.py
pbr/record.html
pbr/record.xlsx
pbr/score.py
pbrats-0.11.1.dist-info/METADATA
pbrats-0.11.1.dist-info/WHEEL
pbrats-0.11.1.dist-info/entry_points.txt
pbrats-0.11.1.dist-info/top_level.txt
pbrats-0.11.1.dist-info/RECORD
