Metadata-Version: 2.1
Name: pbrats
Version: 0.11.1
Summary: Power Bridge Record artistic table system
Home-page: https://gitlab.com/xrgopher/pbrats
Author: xrgopher
Author-email: xrgopher@outlook.com
License: UNKNOWN
Platform: UNKNOWN
Classifier: Programming Language :: Python :: 3
Classifier: License :: OSI Approved :: GNU General Public License v3 (GPLv3)
Classifier: Operating System :: OS Independent
Requires-Python: >=3.6
Requires-Dist: repackage
Requires-Dist: bridge-utils
Requires-Dist: pandas
Requires-Dist: openpyxl
Requires-Dist: xlsxwriter
